gadify/__init__.py
gadify/dates.py
gadify/decimals.py
gadify/fields.py
gadify/json.py
gadify/lists.py
gadify/modules.py
gadify/paths.py
gadify/streams.py
gadify/strings.py
gadify/temp.py
gadify/urls.py
gadify/const/__init__.py
gadify/const/encoding.py
gadify/const/regexp.py
gadify/const/symbols.py
gadify/const/unicode.py
tests/__init__.py
tests/test_init.py
gadify-0.0.5.dist-info/LICENSE
gadify-0.0.5.dist-info/METADATA
gadify-0.0.5.dist-info/WHEEL
gadify-0.0.5.dist-info/top_level.txt
gadify-0.0.5.dist-info/RECORD
