Metadata-Version: 2.1
Name: gadify
Version: 0.0.5
Summary: A lightweight utility library for building clean and reusable data manipulation functions.
Home-page: https://github.com/AlexDemure/gadify
Author: Alexander Grishchenko
Author-email: alexanderdemure@gmail.com
Classifier: Programming Language :: Python :: 3
Classifier: License :: OSI Approved :: MIT License
Classifier: Operating System :: OS Independent
Requires-Python: >=3.8
License-File: LICENSE
